{ "apiTimestamp": 1682489416, "apiStatus": "success", "apiCode": 200, "apiResult": [ { "id": 5824, "english": "That\u2019s right. I\u2019m nice. After everything that has happened in my life, I still haven\u2019t gone after anyone or anything in revenge. If I were normal I would have destroyed the world by now. In a sense it makes me a savior of sorts.", "indo": "Betul sekali. saya baik. Setelah semua yang terjadi dalam hidupku, aku masih belum mengejar siapa pun atau apa pun untuk membalas dendam. Jika saya normal, saya akan menghancurkan dunia sekarang. Dalam arti tertentu itu membuat saya menjadi semacam penyelamat.", "character": "Hachiman Hikigaya", "anime": "Yahari Ore No Seishun Love Come Wa Machigatteiru" } ] }
