{ "apiTimestamp": 1682486204, "apiStatus": "success", "apiCode": 200, "apiResult": [ { "id": 5521, "english": "The system created by the divine ones segregates every single person into his living assignment in the world, determines his roles and controls them...the melancholy voices of those born into this world have pierced the depths of my heart. I feel the need to do something for them without discriminating against anyone.", "indo": "Sistem yang diciptakan oleh para dewa memisahkan setiap orang ke dalam tugas hidupnya di dunia, menentukan perannya dan mengendalikan mereka...suara melankolis dari mereka yang lahir ke dunia ini telah menembus lubuk hatiku. Saya merasa perlu melakukan sesuatu untuk mereka tanpa membeda-bedakan siapa pun.", "character": "Celestin", "anime": "Aah! Megami-Sama" } ] }
